hotglue_etl_exceptions/__init__.py
hotglue_etl_exceptions-0.1.0.dist-info/METADATA
hotglue_etl_exceptions-0.1.0.dist-info/WHEEL
hotglue_etl_exceptions-0.1.0.dist-info/top_level.txt
hotglue_etl_exceptions-0.1.0.dist-info/RECORD
